{
	"@metadata": {
		"authors": [
			"Умар"
		]
	},
	"pywikibot-cosmetic-changes": "; косметикийн хийцам",
	"pywikibot-enter-category-name": "Дехар до, дӀайазйе категорин цӀе:",
	"pywikibot-enter-file-links-processing": "Муьлхачу файлан хьажоргаш кечйан йезаш йу?",
	"pywikibot-enter-finished-browser": "Браузер чохь хийцам бинчултӀехьа таӀае Enter.",
	"pywikibot-enter-namespace-number": "Дехар до, цӀерийн меттиигийн лоьмар йазйе:",
	"pywikibot-enter-new-text": "Дехар до, керла йоза йазде:",
	"pywikibot-enter-page-processing": "Муьлха агӀо кечйан йезаш йу?",
	"pywikibot-enter-xml-filename": "Дехар до, дампа XML файлан цӀе йазйе:",
	"pywikibot-fixes-isbn": "бот: йухакхоллар → ISBN"
}
