{
	"@metadata": {
		"authors": [
			"Jon Harald Søby",
			"Nghtwlkr",
			"SuperPotato"
		]
	},
	"category_redirect-add-template": "Robot: legger til kategoriomdirigeringsmal for vedlikehold",
	"category_redirect-change-category": "Robot: endre omdirigert kategori [[:%(oldCatLink)s|%(oldCatTitle)s]] to [[:%(newCatLink)s|%(newCatTitle)s]]",
	"category_redirect-comment": "Vedlikeholdsbot for kategoriomdirigering",
	"category_redirect-edit-request": "Det har blitt oppdaget at følgende beskyttede sider krever oppdateringer til kategorilenker: %(itemlist)s",
	"category_redirect-edit-request-item": "* %(title)s er i %(oldcat)s, som er en omdirigering til %(newcat)s",
	"category_redirect-fix-double": "Robot: Retter dobbel omdirigering",
	"category_redirect-log-add-failed": "* Kunne ikke legge til [[%(ns)s%(template)s]] på %(oldcat)s",
	"category_redirect-log-added": "* La til [[%(ns)s%(template)s]] på %(oldcat)s",
	"category_redirect-log-double": "* Fikset dobbel omdirigering: %(oldcat)s → %(newcat)s → %(targetcat)s",
	"category_redirect-log-failed": "** Feilet: %(error)s",
	"category_redirect-log-false-positive": "* Uventet ikke-omdirigering: %(oldcat)s",
	"category_redirect-log-ignoring": "* Ignorerer %(oldcat)s",
	"category_redirect-log-loop": "* Omdirigeringssløyfe fra %(oldcat)s",
	"category_redirect-log-moved": "* %(oldcat)s: %(found)d funnet, %(moved)d flyttet",
	"category_redirect-log-new": "Nye omdirigeringer siden forrige rapport:",
	"category_redirect-log-not-loaded": "* Kunne ikke laste %(oldcat)s; ignorerer",
	"category_redirect-log-skipping": "* Hopper over %(oldcat)s; i venteperiode",
	"category_redirect-older-logs": "'''[%(oldlogs)s Eldre logger]'''",
	"category_redirect-problem-hard": "# %(oldcat)s er en hard omdirigering til %(page)s",
	"category_redirect-problem-redirects": "# %(oldcat)s omdirigerer til %(redpage)s",
	"category_redirect-problem-self-linked": "# %(oldcat)s er en selvlenkende omdirigering"
}
