{
	"@metadata": {
		"authors": [
			"AZISS",
			"Khutuck",
			"PPerviz",
			"Wertuose"
		]
	},
	"category-adding": "Bot: [[:Category:%(newcat)s|%(newcat)s]] kateqoriyası əlavə olunur",
	"category-also-in": "(həmçinin %(alsocat)s kateqoriyasında)",
	"category-changing": "Bot: %(oldcat)s kateqoriyası %(newcat)s kateqoriyasına dəyişdirildi",
	"category-listifying": "Bot: %(fromcat)s üçün ({{PLURAL:%(num)d|elementdən}}) ibarət siyahı hazırlanır",
	"category-removing": "Bot: %(oldcat)s kateqoriyasından istisna edilir",
	"category-renamed": "Bot: %(oldcat)s tərəfindən yeri dəyişdirilib. Müəlliflər: %(authors)s",
	"category-replacing": "Bot: %(oldcat)s kateqoriyası %(newcat)s kateqoriyası ilə əvəzləndi",
	"category-section-title": "%(oldcat)s keçmiş səhifə tarixçəsi",
	"category-version-history": "Bot: Keçmiş %(oldcat)s kateqoriyasının yaddaşa saxlanmış versiyalar tarixçəsi",
	"category-was-disbanded": "Bot: Kateqoriya ləğv edildi",
	"category-was-moved": "Bot: Kateqoriyanın yeri dəyişdirilib: [[:Category:%(newcat)s|%(title)s]]"
}
